[
  {
    "id": 6138,
    "arabic": "جَزَآؤُهُمْ عِندَ رَبِّهِمْ جَنَّٰتُ عَدْنٍۢ تَجْرِى مِن تَحْتِهَا ٱلْأَنْهَٰرُ خَٰلِدِينَ فِيهَآ أَبَدًۭا ۖ رَّضِىَ ٱللَّهُ عَنْهُمْ وَرَضُوا۟ عَنْهُ ۚ ذَٰلِكَ لِمَنْ خَشِىَ رَبَّهُۥ",
    "turkish": "Rableri katında onların mükâfatı, altlarından ırmaklar akan Adn cennetleridir. Orada ebedî olarak kalacaklardır. Allah onlardan razı olmuş, onlar da O'ndan razı olmuşlardır. İşte bu mükâfat, Rabbine saygı gösterene mahsustur.",
    "verseNumber": 8,
    "surahNumber": 98,
    "surahName": "سُورَةُ البَيِّنَةِ",
    "englishName": "Al-Bayyina"
  },
  {
    "id": 6139,
    "arabic": "بِسْمِ ٱللَّهِ ٱلرَّحْمَٰنِ ٱلرَّحِيمِ إِذَا زُلْزِلَتِ ٱلْأَرْضُ زِلْزَالَهَا",
    "turkish": "Yer o yaman sarsıntı ile sarsıldığı,",
    "verseNumber": 1,
    "surahNumber": 99,
    "surahName": "سُورَةُ الزَّلۡزَلَةِ",
    "englishName": "Az-Zalzala"
  },
  {
    "id": 6140,
    "arabic": "وَأَخْرَجَتِ ٱلْأَرْضُ أَثْقَالَهَا",
    "turkish": "Yer, içindeki ağırlıkları çıkarıp dışarı attığı,",
    "verseNumber": 2,
    "surahNumber": 99,
    "surahName": "سُورَةُ الزَّلۡزَلَةِ",
    "englishName": "Az-Zalzala"
  },
  {
    "id": 6141,
    "arabic": "وَقَالَ ٱلْإِنسَٰنُ مَا لَهَا",
    "turkish": "Ve insan: \"Ona ne oluyor?\" dediği zaman.",
    "verseNumber": 3,
    "surahNumber": 99,
    "surahName": "سُورَةُ الزَّلۡزَلَةِ",
    "englishName": "Az-Zalzala"
  },
  {
    "id": 6142,
    "arabic": "يَوْمَئِذٍۢ تُحَدِّثُ أَخْبَارَهَا",
    "turkish": "O gün yer, Rabbinin ona vahyetmesiyle haberlerini anlatacaktır.",
    "verseNumber": 4,
    "surahNumber": 99,
    "surahName": "سُورَةُ الزَّلۡزَلَةِ",
    "englishName": "Az-Zalzala"
  },
  {
    "id": 6143,
    "arabic": "بِأَنَّ رَبَّكَ أَوْحَىٰ لَهَا",
    "turkish": "O gün yer, Rabbinin ona vahyetmesiyle haberlerini anlatacaktır.",
    "verseNumber": 5,
    "surahNumber": 99,
    "surahName": "سُورَةُ الزَّلۡزَلَةِ",
    "englishName": "Az-Zalzala"
  },
  {
    "id": 6144,
    "arabic": "يَوْمَئِذٍۢ يَصْدُرُ ٱلنَّاسُ أَشْتَاتًۭا لِّيُرَوْا۟ أَعْمَٰلَهُمْ",
    "turkish": "O gün insanlar, amellerinin karşılığı kendilerine gösterilmek üzere bölük bölük çıkacaklardır.",
    "verseNumber": 6,
    "surahNumber": 99,
    "surahName": "سُورَةُ الزَّلۡزَلَةِ",
    "englishName": "Az-Zalzala"
  },
  {
    "id": 6145,
    "arabic": "فَمَن يَعْمَلْ مِثْقَالَ ذَرَّةٍ خَيْرًۭا يَرَهُۥ",
    "turkish": "Her kim zerre kadar hayır işlemişse onu görecektir.",
    "verseNumber": 7,
    "surahNumber": 99,
    "surahName": "سُورَةُ الزَّلۡزَلَةِ",
    "englishName": "Az-Zalzala"
  },
  {
    "id": 6146,
    "arabic": "وَمَن يَعْمَلْ مِثْقَالَ ذَرَّةٍۢ شَرًّۭا يَرَهُۥ",
    "turkish": "Her kim, zerre kadar şer işlemişse onu görecektir.",
    "verseNumber": 8,
    "surahNumber": 99,
    "surahName": "سُورَةُ الزَّلۡزَلَةِ",
    "englishName": "Az-Zalzala"
  },
  {
    "id": 6147,
    "arabic": "بِسْمِ ٱللَّهِ ٱلرَّحْمَٰنِ ٱلرَّحِيمِ وَٱلْعَٰدِيَٰتِ ضَبْحًۭا",
    "turkish": "O harıl harıl (savaşa) koşanlara,",
    "verseNumber": 1,
    "surahNumber": 100,
    "surahName": "سُورَةُ العَادِيَاتِ",
    "englishName": "Al-Aadiyaat"
  },
  {
    "id": 6148,
    "arabic": "فَٱلْمُورِيَٰتِ قَدْحًۭا",
    "turkish": "(Tırnaklarıyla yerden) ateş çıkaranlara,",
    "verseNumber": 2,
    "surahNumber": 100,
    "surahName": "سُورَةُ العَادِيَاتِ",
    "englishName": "Al-Aadiyaat"
  },
  {
    "id": 6149,
    "arabic": "فَٱلْمُغِيرَٰتِ صُبْحًۭا",
    "turkish": "Sabahleyin akın edenlere,",
    "verseNumber": 3,
    "surahNumber": 100,
    "surahName": "سُورَةُ العَادِيَاتِ",
    "englishName": "Al-Aadiyaat"
  },
  {
    "id": 6150,
    "arabic": "فَأَثَرْنَ بِهِۦ نَقْعًۭا",
    "turkish": "Tozu dumana karıştıranlara,",
    "verseNumber": 4,
    "surahNumber": 100,
    "surahName": "سُورَةُ العَادِيَاتِ",
    "englishName": "Al-Aadiyaat"
  },
  {
    "id": 6151,
    "arabic": "فَوَسَطْنَ بِهِۦ جَمْعًا",
    "turkish": "Derken bir topluluğun ortasına dalanlara yemin ederim ki,",
    "verseNumber": 5,
    "surahNumber": 100,
    "surahName": "سُورَةُ العَادِيَاتِ",
    "englishName": "Al-Aadiyaat"
  },
  {
    "id": 6152,
    "arabic": "إِنَّ ٱلْإِنسَٰنَ لِرَبِّهِۦ لَكَنُودٌۭ",
    "turkish": "Şüphesiz insan, Rabbine karşı çok nankördür.",
    "verseNumber": 6,
    "surahNumber": 100,
    "surahName": "سُورَةُ العَادِيَاتِ",
    "englishName": "Al-Aadiyaat"
  },
  {
    "id": 6153,
    "arabic": "وَإِنَّهُۥ عَلَىٰ ذَٰلِكَ لَشَهِيدٌۭ",
    "turkish": "Ve kendisi de buna şahittir.",
    "verseNumber": 7,
    "surahNumber": 100,
    "surahName": "سُورَةُ العَادِيَاتِ",
    "englishName": "Al-Aadiyaat"
  },
  {
    "id": 6154,
    "arabic": "وَإِنَّهُۥ لِحُبِّ ٱلْخَيْرِ لَشَدِيدٌ",
    "turkish": "Gerçekten o dünya malını çok sevdiği için katıdır.",
    "verseNumber": 8,
    "surahNumber": 100,
    "surahName": "سُورَةُ العَادِيَاتِ",
    "englishName": "Al-Aadiyaat"
  },
  {
    "id": 6155,
    "arabic": "۞ أَفَلَا يَعْلَمُ إِذَا بُعْثِرَ مَا فِى ٱلْقُبُورِ",
    "turkish": "Bilmiyor mu ki, kabirlerin içindekiler fırlatılacak.",
    "verseNumber": 9,
    "surahNumber": 100,
    "surahName": "سُورَةُ العَادِيَاتِ",
    "englishName": "Al-Aadiyaat"
  }
]